termsandconditions/__init__.py
termsandconditions/admin.py
termsandconditions/apps.py
termsandconditions/decorators.py
termsandconditions/forms.py
termsandconditions/locale/en/LC_MESSAGES/django.mo
termsandconditions/locale/en/LC_MESSAGES/django.po
termsandconditions/locale/pt_BR/LC_MESSAGES/django.po
termsandconditions/locale/ru/LC_MESSAGES/django.mo
termsandconditions/locale/ru/LC_MESSAGES/django.po
termsandconditions/management/__init__.py
termsandconditions/management/commands/__init__.py
termsandconditions/management/commands/remove_old_version_acceptance.py
termsandconditions/middleware.py
termsandconditions/migrations/0001_initial.py
termsandconditions/migrations/0002_termsandconditions_info.py
termsandconditions/migrations/0003_auto_20170627_1217.py
termsandconditions/migrations/0004_auto_20201107_0711.py
termsandconditions/migrations/__init__.py
termsandconditions/models.py
termsandconditions/pipeline.py
termsandconditions/signals.py
termsandconditions/static/termsandconditions/css/modal.css
termsandconditions/static/termsandconditions/css/view_accept.css
termsandconditions/static/termsandconditions/js/modal.js
termsandconditions/templates/termsandconditions/snippets/termsandconditions.html
termsandconditions/templates/termsandconditions/tc_accept_terms.html
termsandconditions/templates/termsandconditions/tc_email_terms.html
termsandconditions/templates/termsandconditions/tc_email_terms_form.html
termsandconditions/templates/termsandconditions/tc_print_terms.html
termsandconditions/templates/termsandconditions/tc_view_terms.html
termsandconditions/templatetags/__init__.py
termsandconditions/templatetags/terms_tags.py
termsandconditions/tests.py
termsandconditions/urls.py
termsandconditions/views.py
django_termsandconditions-2.0.12.dist-info/METADATA
django_termsandconditions-2.0.12.dist-info/WHEEL
django_termsandconditions-2.0.12.dist-info/LICENSE.txt
django_termsandconditions-2.0.12.dist-info/RECORD
