Metadata-Version: 2.1
Name: django-termsandconditions
Version: 2.0.12
Summary: Django app that enables users to accept terms and conditions of a site.
Home-page: https://github.com/cyface/django-termsandconditions
License: BSD
Author: Tim White
Author-email: tim@cyface.com
Requires-Python: >=3.7.2,<4.0
Classifier: Development Status :: 5 - Production/Stable
Classifier: Framework :: Django
Classifier: Intended Audience :: Developers
Classifier: License :: OSI Approved :: MIT License
Classifier: License :: Other/Proprietary License
Classifier: Operating System :: OS Independent
Classifier: Programming Language :: Python :: 3
Classifier: Programming Language :: Python :: 3.8
Classifier: Programming Language :: Python :: 3.9
Classifier: Programming Language :: Python :: 3.10
Classifier: Programming Language :: Python :: 3.11
Classifier: Programming Language :: Python :: 3.6
Classifier: Programming Language :: Python :: 3.7
Classifier: Programming Language :: Python :: 3.8
Classifier: Topic :: Internet :: WWW/HTTP
Requires-Dist: Django (>2.2)
